{
  "version": "5",
  "dialect": "sqlite",
  "id": "aa8fa9b4-7f4f-4a02-a0e2-8e99423b36be",
  "prevId": "719b5825-7ebd-4a3f-a117-7693596e3c02",
  "tables": {
    "todos": {
      "name": "todos",
      "columns": {
        "id": {
          "name": "id",
          "type": "integer",
          "primaryKey": true,
          "notNull": true,
          "autoincrement": true
        },
        "title": {
          "name": "title",
          "type": "text",
          "primaryKey": false,
          "notNull": true,
          "autoincrement": false
        },
        "done": {
          "name": "done",
          "type": "integer",
          "primaryKey": false,
          "notNull": false,
          "autoincrement": false,
          "default": false
        },
        "created_at": {
          "name": "created_at",
          "type": "text",
          "primaryKey": false,
          "notNull": false,
          "autoincrement": false,
          "default": "CURRENT_TIMESTAMP"
        }
      },
      "indexes": {},
      "foreignKeys": {},
      "compositePrimaryKeys": {},
      "uniqueConstraints": {}
    }
  },
  "enums": {},
  "_meta": {
    "schemas": {},
    "tables": {
      "\"todo\"": "\"todos\""
    },
    "columns": {}
  }
}